{
	"label": "Tags",
	"entries": [
		{
			"id": "-1 forward",
			"name": "-1 à suivre"
		},
		{
			"id": "+1 damage",
			"name": "+1 aux dégâts"
		},
		{
			"id": "+1 ongoing",
			"name": "+1 à continuer",
			"description": ""
		},
		{
			"id": "+2 damage",
			"name": "+2 aux dégâts"
		},
		{
			"id": "+3 damage",
			"name": "+3 aux dégâts"
		},
		{
			"id": "1 ammo",
			"name": "1 munition"
		},
		{
			"id": "1 armor",
			"name": "1 armor"
		},
		{
			"id": "1 piercing",
			"name": "1 en dégât perforant"
		},
		{
			"id": "2 ammo",
			"name": "2 munitions"
		},
		{
			"id": "2 armor",
			"name": "2 armor"
		},
		{
			"id": "2 piercing",
			"name": "2 en dégâts perforants"
		},
		{
			"id": "3 ammo",
			"name": "3 munitions"
		},
		{
			"id": "3 armor",
			"name": "3 armor"
		},
		{
			"id": "3 piercing",
			"name": "3 en dégâts perforants"
		},
		{
			"id": "4 ammo",
			"name": "4 munitions"
		},
		{
			"id": "Amorphous",
			"name": "Amorphous"
		},
		{
			"id": "Applied",
			"name": "Applied"
		},
		{
			"id": "Awkward",
			"name": "Awkward"
		},
		{
			"id": "Cautious",
			"name": "Cautious"
		},
		{
			"id": "Close",
			"name": "Close"
		},
		{
			"id": "Clumsy",
			"name": "Clumsy"
		},
		{
			"id": "Construct",
			"name": "Construct"
		},
		{
			"id": "Dangerous",
			"name": "Dangerous"
		},
		{
			"id": "Devious",
			"name": "Devious"
		},
		{
			"id": "Far",
			"name": "Far"
		},
		{
			"id": "Forceful",
			"name": "Forceful"
		},
		{
			"id": "Group",
			"name": "Group"
		},
		{
			"id": "Hand",
			"name": "Hand"
		},
		{
			"id": "Hoarder",
			"name": "Hoarder"
		},
		{
			"id": "Horde",
			"name": "Horde"
		},
		{
			"id": "Huge",
			"name": "Huge"
		},
		{
			"id": "Ignores Armor",
			"name": "Ignores Armor"
		},
		{
			"id": "Intelligent",
			"name": "Intelligent"
		},
		{
			"id": "Large",
			"name": "Large"
		},
		{
			"id": "Magical",
			"name": "Magical"
		},
		{
			"id": "Messy",
			"name": "Messy"
		},
		{
			"id": "Near",
			"name": "Near"
		},
		{
			"id": "Organized",
			"name": "Organized"
		},
		{
			"id": "Planar",
			"name": "Planar"
		},
		{
			"id": "Precise",
			"name": "Precise"
		},
		{
			"id": "Ration",
			"name": "Ration"
		},
		{
			"id": "Reach",
			"name": "Reach"
		},
		{
			"id": "Reload",
			"name": "Reload"
		},
		{
			"id": "Requires",
			"name": "Requires"
		},
		{
			"id": "Requires Dwarf",
			"name": "Requires Dwarf"
		},
		{
			"id": "Slow",
			"name": "Slow"
		},
		{
			"id": "Small",
			"name": "Small"
		},
		{
			"id": "Solitary",
			"name": "Solitary"
		},
		{
			"id": "Stealthy",
			"name": "Stealthy"
		},
		{
			"id": "Stun",
			"name": "Stun"
		},
		{
			"id": "Terrifying",
			"name": "Terrifying"
		},
		{
			"id": "Thrown",
			"name": "Thrown"
		},
		{
			"id": "Tiny",
			"name": "Tiny"
		},
		{
			"id": "Touch",
			"name": "Touch"
		},
		{
			"id": "Two-handed",
			"name": "Two-handed"
		},
		{
			"id": "Worn",
			"name": "Worn"
		}
	]
}